{
    "todos": [
        {
            "key": "Todo 1 Mockado1"
        },   
        {    
            "key": "Todo 1 Mockado2"
        },   
        {    
            "key": "Todo 1 Mockado3"
        },   
        {    
            "key": "Todo 1 Mockado4"
        },   
        {    
            "key": "Todo 1 Mockado5"
        },   
        {    
            "key": "Todo 1 Mockado6"
        },   
        {    
            "key": "Todo 1 Mockado7"
        },   
        {    
            "key": "Todo 1 Mockado8"
        }
    ]
}